NorrisUtils/BuildConfig.py
NorrisUtils/ConfigLoader.py
NorrisUtils/DingTalkGenius.py
NorrisUtils/FileUtil.py
NorrisUtils/GarbageGenius.py
NorrisUtils/ImageUploadUtils.py
NorrisUtils/RawUtil.py
NorrisUtils/RawUtils.py
NorrisUtils/RequestUtils.py
NorrisUtils/__init__.py
NorrisUtils-1.5.2.dist-info/METADATA
NorrisUtils-1.5.2.dist-info/WHEEL
NorrisUtils-1.5.2.dist-info/top_level.txt
NorrisUtils-1.5.2.dist-info/RECORD
